f5_tts_th/THG2P.py
f5_tts_th/__init__.py
f5_tts_th/cfm.py
f5_tts_th/dit.py
f5_tts_th/modules.py
f5_tts_th/normalize.py
f5_tts_th/tts.py
f5_tts_th/utils.py
f5_tts_th/utils_infer.py
f5_tts_th/data/PhSTrigram.sts
f5_tts_th/data/sylrule.lts
f5_tts_th/data/sylseg.3g
f5_tts_th/data/thai2phone.csv
f5_tts_th/data/thaisyl.dict
f5_tts_th/data/thdict
f5_tts_th-1.0.9.dist-info/METADATA
f5_tts_th-1.0.9.dist-info/WHEEL
f5_tts_th-1.0.9.dist-info/top_level.txt
f5_tts_th-1.0.9.dist-info/RECORD
