Metadata-Version: 2.4
Name: f5-tts-th
Version: 1.0.9
Summary: F5-TTS: Text-to-Speech (TTS) ภาษาไทย — เครื่องมือสร้างเสียงพูดจากข้อความด้วยเทคนิค Flow Matching
Requires-Dist: cached_path
Requires-Dist: jieba
Requires-Dist: librosa
Requires-Dist: matplotlib
Requires-Dist: numpy<=1.26.4
Requires-Dist: pydub
Requires-Dist: pypinyin
Requires-Dist: soundfile
Requires-Dist: torch>=2.0.0
Requires-Dist: torchaudio>=2.0.0
Requires-Dist: torchdiffeq
Requires-Dist: tqdm>=4.65.0
Requires-Dist: transformers
Requires-Dist: vocos
Requires-Dist: x_transformers>=1.31.14
Requires-Dist: pythainlp
Requires-Dist: python-crfsuite
Requires-Dist: ssg
Dynamic: description
Dynamic: description-content-type
Dynamic: requires-dist
Dynamic: summary
